dolon/__init__.py
dolon/_version.py
dolon/db_conn.py
dolon/exceptions.py
dolon/profiler.py
dolon/speedometer.py
dolon/trace_client.py
dolon/utils.py
dolon/impl/__init__.py
dolon/impl/constants.py
dolon/impl/db_conn_impl.py
dolon/impl/db_stats.py
dolon/impl/trace_client_impl.py
dolon/impl/utils_impl.py
dolon-0.2.0.dist-info/LICENSE
dolon-0.2.0.dist-info/METADATA
dolon-0.2.0.dist-info/WHEEL
dolon-0.2.0.dist-info/top_level.txt
dolon-0.2.0.dist-info/RECORD
