Metadata-Version: 2.1
Name: dolon
Version: 0.2.0
Summary: A performance tracer application.
Home-page: UNKNOWN
Author: UNKNOWN
Author-email: UNKNOWN
License: UNKNOWN
Platform: UNKNOWN
Requires-Dist: aiohttp
Requires-Dist: asyncpg
Requires-Dist: psutil
